{
  "app_name": "task_tracker",
  "saved_at": "2026-03-23T00:18:25.362336",
  "spec_text": "# App Specification: Task Tracker\n\n## 1. Overview\nThe Task Tracker is a comprehensive application designed to help users manage their personal or professional tasks efficiently. It includes features such as task categorization, setting deadlines, scheduling reminders, and collaboration with others. The app aims to provide a user-friendly interface for creating, reading, updating, and deleting tasks while ensuring secure authentication and authorization.\n\n## 2. App Type & Platform\n- **App Type:** Task Tracker\n- **Platform:** Web-based application\n\n## 3. Core Features\n1. **Task Management:**\n   - Create new tasks with categories, deadlines, and descriptions.\n   - View all tasks with filters for categories and deadlines.\n   - Edit existing tasks.\n   - Delete tasks.\n\n2. **Reminders:**\n   - Set reminders for tasks to notify users via email or in-app notifications.\n\n3. **Collaboration:**\n   - Share tasks with other users.\n   - Assign tasks to team members.\n   - Comment on tasks and collaborate in real-time.\n\n4. **User Authentication:**\n   - Register new users.\n   - Login and logout functionality.\n   - Secure user profiles.\n\n## 4. Technology Stack\n\n| Layer                | Technology       | Version     | Reason                                                                 |\n|----------------------|------------------|-------------|------------------------------------------------------------------------|\n| Front-end            | React            | Latest      | Provides a fast and interactive user interface.                          |\n|                      | Next.js          | Latest      | Enables server-side rendering and API routes for the front-end.         |\n| Back-end             | Node.js          | 16.x        | A popular choice for building scalable network applications.              |\n|                      | Next.js          | Latest      | Integrates well with React and provides API routes for the back-end.     |\n| ORM                  | TypeORM          | Latest      | Provides a robust ORM solution for database interactions.                |\n| Database             | PostgreSQL       | 13.x        | A reliable and feature-rich relational database management system.         |\n| Authentication/Authorization | JWT            | Latest      | Securely handles user authentication and authorization.               |\n\n## 5. Architecture\n- **Design Pattern:** Monolithic architecture.\n- **Folder/Project Structure:**\n\n```\ntask-tracker/\n\u251c\u2500\u2500 api/\n\u2502   \u251c\u2500\u2500 auth/\n\u2502   \u2502   \u251c\u2500\u2500 register.js\n\u2502   \u2502   \u251c\u2500\u2500 login.js\n\u2502   \u2502   \u2514\u2500\u2500 profile.js\n\u2502   \u2514\u2500\u2500 tasks/\n\u2502       \u251c\u2500\u2500 create.js\n\u2502       \u251c\u2500\u2500 read.js\n\u2502       \u251c\u2500\u2500 update.js\n\u2502       \u2514\u2500\u2500 delete.js\n\u251c\u2500\u2500 components/\n\u2502   \u251c\u2500\u2500 TaskList.js\n\u2502   \u251c\u2500\u2500 TaskForm.js\n\u2502   \u2514\u2500\u2500 Reminder.js\n\u251c\u2500\u2500 pages/\n\u2502   \u251c\u2500\u2500 index.js\n\u2502   \u251c\u2500\u2500 login.js\n\u2502   \u251c\u2500\u2500 register.js\n\u2502   \u2514\u2500\u2500 tasks.js\n\u251c\u2500\u2500 public/\n\u2502   \u251c\u2500\u2500 favicon.ico\n\u2502   \u2514\u2500\u2500 images/\n\u251c\u2500\u2500 styles/\n\u2502   \u251c\u2500\u2500 globals.css\n\u2502   \u2514\u2500\u2500 components/\n\u251c\u2500\u2500 models/\n\u2502   \u251c\u2500\u2500 User.js\n\u2502   \u2514\u2500\u2500 Task.js\n\u251c\u2500\u2500 utils/\n\u2502   \u251c\u2500\u2500 auth.js\n\u2502   \u2514\u2500\u2500 api.js\n\u251c\u2500\u2500 .env\n\u251c\u2500\u2500 package.json\n\u2514\u2500\u2500 next.config.js\n```\n\n- **Data Flow Description:**\n  - The front-end sends requests to the API endpoints defined in the `api/` directory.\n  - The back-end processes these requests using Next.js API routes and interacts with the PostgreSQL database via TypeORM.\n  - Responses from the back-end are sent back to the front-end, which updates the user interface accordingly.\n\n## 6. Data Models\n- **User Model:**\n  ```javascript\n  import { Entity, PrimaryGeneratedColumn, Column } from 'typeorm';\n\n  @Entity()\n  export class User {\n    @PrimaryGeneratedColumn()\n    id: number;\n\n    @Column()\n    username: string;\n\n    @Column()\n    email: string;\n\n    @Column()\n    password: string;\n  }\n  ```\n\n- **Task Model:**\n  ```javascript\n  import { Entity, PrimaryGeneratedColumn, Column, ManyToOne } from 'typeorm';\n  import { User } from './User';\n\n  @Entity()\n  export class Task {\n    @PrimaryGeneratedColumn()\n    id: number;\n\n    @Column()\n    title: string;\n\n    @Column()\n    description: string;\n\n    @Column()\n    category: string;\n\n    @Column()\n    deadline: Date;\n\n    @ManyToOne(() => User, user => user.tasks)\n    user: User;\n  }\n  ```\n\n## 7. API Design\n- **User Authentication:**\n  - `POST /api/auth/register`: Register a new user.\n    ```json\n    {\n      \"username\": \"string\",\n      \"email\": \"string\",\n      \"password\": \"string\"\n    }\n    ```\n  - `POST /api/auth/login`: Authenticate a user and return a JWT token.\n    ```json\n    {\n      \"email\": \"string\",\n      \"password\": \"string\"\n    }\n    ```\n  - `GET /api/auth/profile`: Get the current user's profile (protected by JWT).\n\n- **Task Management:**\n  - `POST /api/tasks`: Create a new task.\n    ```json\n    {\n      \"title\": \"string\",\n      \"description\": \"string\",\n      \"category\": \"string\",\n      \"deadline\": \"date\"\n    }\n    ```\n  - `GET /api/tasks`: Retrieve all tasks (with optional filters like category, deadline).\n  - `GET /api/tasks/:id`: Retrieve a specific task by ID.\n  - `PUT /api/tasks/:id`: Update an existing task.\n    ```json\n    {\n      \"title\": \"string\",\n      \"description\": \"string\",\n      \"category\": \"string\",\n      \"deadline\": \"date\"\n    }\n    ```\n  - `DELETE /api/tasks/:id`: Delete a task.\n\n## 8. User Authentication (if applicable)\n- **JWT Implementation:**\n  - The app uses JSON Web Tokens (JWT) for user authentication and authorization.\n  - JWT tokens are generated upon successful login and must be included in the Authorization header for protected routes.\n\n## 9. Development Environment Setup\n1. **Front-end:**\n   ```bash\n   npx create-next-app@latest task-tracker\n   cd task-tracker\n   npm install react react-dom next\n   ```\n\n2. **Back-end:**\n   ```bash\n   npm init -y\n   npm install express typeorm pg jsonwebtoken bcryptjs\n   ```\n\n3. **Database Setup:**\n   - Install PostgreSQL and create a new database.\n   - Configure TypeORM to connect to the PostgreSQL database.\n\n4. **Environment Variables:**\n   - Create a `.env` file in the root directory with the following variables:\n     ```plaintext\n     DATABASE_URL=postgres://username:password@localhost:5432/task-tracker\n     JWT_SECRET=your_jwt_secret_key\n     ```\n\n## 10. Build & Deployment\n- **Local Development:**\n  - Start the front-end development server:\n    ```bash\n    npm run dev\n    ```\n  - Start the back-end server:\n    ```bash\n    node server.js\n    ```\n\n- **Deployment on VPS Server:**\n  - Install Node.js and PostgreSQL on your VPS.\n  - Clone the repository to your VPS.\n  - Set up environment variables in a `.env` file.\n  - Build the front-end application:\n    ```bash\n    npm run build\n    ```\n  - Start the back-end server:\n    ```bash\n    node server.js\n    ```\n\n## 11. Open Questions / Future Enhancements\n- **Enhanced Collaboration:**\n  - Implement real-time collaboration features using WebSockets.\n  \n- **Task Prioritization:**\n  - Add task prioritization levels (e.g., high, medium, low).\n\n- **Mobile App Integration:**\n  - Develop a mobile app version of the Task Tracker.\n\n- **Analytics Dashboard:**\n  - Create an analytics dashboard to track user activity and task progress.\n\nThis comprehensive specification document outlines the development plan for the Task Tracker application, ensuring that all core features are covered with a robust technology stack and architecture.",
  "history": [
    {
      "role": "system",
      "content": "You are a senior software architect and product consultant. \nYour role is to have an in-depth discussion with the user about their app idea. \n\nGuidelines:\n- Ask ONE or TWO focused questions at a time (don't overwhelm the user)\n- When the user shares an opinion, acknowledge it, give honest feedback (pros/cons), \n  and either confirm their choice or suggest a better alternative with clear reasoning\n- Keep track of all decisions made (stack, architecture, features, etc.)\n- Be conversational and concise \u2014 avoid walls of text\n- Cover: app type, core features, tech stack, architecture, data storage, APIs, auth, deployment\n- Once enough details are gathered, encourage the user to type 'done' to generate the spec"
    },
    {
      "role": "human",
      "content": "The user wants to build: \"task tracker\"\n\nStart by briefly acknowledging their idea enthusiastically, then ask your first focused question to understand the core requirements. Be concise."
    },
    {
      "role": "ai",
      "content": "Great idea! A task tracker can be incredibly useful for managing personal or professional tasks efficiently. \n\nTo get started, could you tell me about the primary features you envision for this app? For example, do you want it to include categories, deadlines, reminders, collaboration with others, or something else?"
    },
    {
      "role": "human",
      "content": "yes all those"
    },
    {
      "role": "ai",
      "content": "That's fantastic! Including categories, deadlines, reminders, and collaboration will make your task tracker quite comprehensive. \n\nNext, let's consider the tech stack. Do you have any preferences for front-end technologies (e.g., React, Angular, Vue.js) or back-end technologies (e.g., Node.js, Django, Ruby on Rails)? If not, I can suggest some popular choices based on common use cases and community support."
    },
    {
      "role": "human",
      "content": "i want reactjs with nextjs for frontend and nextjs with typeorm for backend and JWT for authentication and authorization."
    },
    {
      "role": "ai",
      "content": "Great choice! React with Next.js is a powerful combination for building modern web applications, and using TypeORM with Next.js for the backend provides robust ORM capabilities. JWT for authentication and authorization is also a solid choice.\n\nLet's confirm the stack:\n- Front-end: React + Next.js\n- Back-end: Node.js (with Next.js) + TypeORM\n- Authentication/Authorization: JWT\n\nIs this correct?"
    },
    {
      "role": "human",
      "content": "yes"
    },
    {
      "role": "ai",
      "content": "Perfect! Now, let's discuss the architecture. Given your requirements and chosen tech stack, a microservices architecture could be beneficial for scalability and maintainability. However, for simplicity, we can start with a monolithic architecture where both the front-end and back-end are integrated into one application.\n\nWould you like to proceed with a monolithic architecture or explore a microservices approach?"
    },
    {
      "role": "human",
      "content": "monolithic"
    },
    {
      "role": "ai",
      "content": "Alright, let's go with a monolithic architecture. This will make development and deployment simpler initially.\n\nNext, let's talk about data storage. Since you're using TypeORM, which is an ORM for Node.js, you'll need a database to store your task data. Common choices include PostgreSQL, MySQL, or MongoDB. What do you think about using PostgreSQL for its reliability and robustness?"
    },
    {
      "role": "human",
      "content": "PostgreSQL"
    },
    {
      "role": "ai",
      "content": "Great choice! PostgreSQL is indeed a reliable and feature-rich database option.\n\nNow, let's discuss APIs. Since this is a monolithic application, we'll need to define the API endpoints that the front-end will interact with. These might include endpoints for creating, reading, updating, and deleting tasks (CRUD operations), as well as handling user authentication.\n\nWould you like to start by defining these API endpoints or dive into specific features first?"
    },
    {
      "role": "human",
      "content": "we will use swager in our application"
    },
    {
      "role": "ai",
      "content": "Using Swagger is a great choice for documenting your APIs. It provides an interactive interface and helps ensure that your API is well-documented and easy to understand.\n\nLet's define the initial API endpoints:\n1. **User Authentication:**\n   - `POST /api/auth/register`: Register a new user.\n   - `POST /api/auth/login`: Authenticate a user and return a JWT token.\n   - `GET /api/auth/profile`: Get the current user's profile (protected by JWT).\n\n2. **Task Management:**\n   - `POST /api/tasks`: Create a new task.\n   - `GET /api/tasks`: Retrieve all tasks (with optional filters like category, deadline).\n   - `GET /api/tasks/:id`: Retrieve a specific task by ID.\n   - `PUT /api/tasks/:id`: Update an existing task.\n   - `DELETE /api/tasks/:id`: Delete a task.\n\nWould you like to proceed with these endpoints or make any changes?"
    },
    {
      "role": "human",
      "content": "ok"
    },
    {
      "role": "ai",
      "content": "Great! Let's move forward with these API endpoints. \n\nNext, let's talk about deployment. For simplicity and ease of use, we can start by deploying the application on Vercel for the front-end and Heroku for the back-end. Both platforms offer good support for Node.js applications and are easy to set up.\n\nWould you like to proceed with Vercel for the front-end and Heroku for the back-end, or do you have other deployment preferences?"
    },
    {
      "role": "human",
      "content": "no. right now we will test in my machine then i will host the application my vps server"
    },
    {
      "role": "ai",
      "content": "Understood! Testing locally on your machine is a great way to ensure everything works as expected before deploying.\n\nTo summarize our decisions so far:\n- App Type: Task Tracker\n- Core Features: Categories, deadlines, reminders, collaboration\n- Tech Stack:\n  - Front-end: React + Next.js\n  - Back-end: Node.js (with Next.js) + TypeORM\n  - Authentication/Authorization: JWT\n- Architecture: Monolithic\n- Data Storage: PostgreSQL\n- APIs: Defined endpoints using Swagger\n\nOnce you're ready to proceed with deployment on your VPS server, let me know. You can type 'done' when you're ready to generate the full specification document."
    }
  ]
}